pycewise/__init__.py
pycewise/reg.py
pycewise/version.py
pycewise-0.1.4.dist-info/LICENSE
pycewise-0.1.4.dist-info/METADATA
pycewise-0.1.4.dist-info/WHEEL
pycewise-0.1.4.dist-info/top_level.txt
pycewise-0.1.4.dist-info/RECORD
