Metadata-Version: 2.1
Name: pycewise
Version: 0.1.4
Summary: Piecewise linear regressions, based on model trees.
Home-page: https://github.com/Ezibenroc/pycewise
Author: Tom Cornebize
Author-email: tom.cornebize@gmail.com
License: MIT
Platform: UNKNOWN
Classifier: License :: OSI Approved :: MIT License
Classifier: Intended Audience :: Science/Research
Classifier: Topic :: Scientific/Engineering
Classifier: Operating System :: OS Independent
Classifier: Programming Language :: Python :: 3.6
Classifier: Programming Language :: Python :: 3.7
Classifier: Programming Language :: Python :: 3.8
